irispy2/__init__.py
irispy2/bot/__init__.py
irispy2/bot/models.py
irispy2/bot/_internal/__init__.py
irispy2/bot/_internal/emitter.py
irispy2/bot/_internal/iris.py
irispy2/compat/pykakaodb/__init__.py
irispy2/compat/pykakaodb/context.py
irispy2/compat/pykakaodb/kakaodb.py
irispy2/compat/pykakaodb/legacy_bot.py
irispy2/compat/pykakaodb/replier.py
irispy2-3.4.2.dist-info/METADATA
irispy2-3.4.2.dist-info/WHEEL
irispy2-3.4.2.dist-info/entry_points.txt
irispy2-3.4.2.dist-info/top_level.txt
irispy2-3.4.2.dist-info/RECORD
