Metadata-Version: 2.4
Name: irispy2
Version: 3.4.2
Author-email: ye-seola <ye-seola@proton.me>
Requires-Python: >=3.9
Requires-Dist: requests<3.0.0,>=2.32.3
Requires-Dist: loguru<0.8.0,>=0.7.3
Requires-Dist: pure-python-adb==0.3.0.dev
Requires-Dist: websockets<16.0.0,>=15.0.1
Provides-Extra: pykakaodb-compat
Requires-Dist: pillow; extra == "pykakaodb-compat"
